Rimma/__init__.py
Rimma-1.0.0.dist-info/LICENSE
Rimma-1.0.0.dist-info/METADATA
Rimma-1.0.0.dist-info/WHEEL
Rimma-1.0.0.dist-info/top_level.txt
Rimma-1.0.0.dist-info/RECORD
